pyeuclid/__init__.py
pyeuclid/engine/__init__.py
pyeuclid/engine/algebraic_system.py
pyeuclid/engine/deductive_database.py
pyeuclid/engine/engine.py
pyeuclid/engine/inference_rule.py
pyeuclid/engine/proof_generator.py
pyeuclid/formalization/__init__.py
pyeuclid/formalization/construction_rule.py
pyeuclid/formalization/diagram.py
pyeuclid/formalization/numericals.py
pyeuclid/formalization/relation.py
pyeuclid/formalization/state.py
pyeuclid/formalization/translation.py
pyeuclid/formalization/utils.py
pyeuclid-1.0.3.dist-info/METADATA
pyeuclid-1.0.3.dist-info/WHEEL
pyeuclid-1.0.3.dist-info/licenses/LICENSE
pyeuclid-1.0.3.dist-info/RECORD
