Metadata-Version: 2.4
Name: pyeuclid
Version: 1.0.3
Summary: PyEuclid: A Versatile Formal Plane Geometry System in Python
Project-URL: Homepage, https://github.com/KellyJDavis/PyEuclid
Project-URL: Repository, https://github.com/KellyJDavis/PyEuclid
Author: Zhaoyu Li
Maintainer-email: Kelly J Davis <kdavis@alum.mit.edu>
License: MIT License
License-File: LICENSE
Keywords: formal proof,geometry,reasoning
Classifier: Development Status :: 4 - Beta
Classifier: Intended Audience :: Science/Research
Classifier: License :: OSI Approved :: MIT License
Classifier: Programming Language :: Python
Classifier: Programming Language :: Python :: 3
Classifier: Programming Language :: Python :: 3.10
Classifier: Programming Language :: Python :: 3.11
Classifier: Programming Language :: Python :: 3.12
Classifier: Topic :: Scientific/Engineering :: Mathematics
Requires-Python: <3.13,>=3.10
Requires-Dist: gurobipy>=12.0.1
Requires-Dist: matplotlib>=3.9.4
Requires-Dist: numpy>=2.0.1
Requires-Dist: stopit>=1.1.2
Requires-Dist: sympy>=1.13.3
Requires-Dist: tqdm>=4.67.1
Requires-Dist: z3-solver>=4.14.1.0
